simple_google_spreadsheet/__init__.py
simple_google_spreadsheet/spreadsheet.py
simple_google_spreadsheet-0.0.4.dist-info/LICENSE
simple_google_spreadsheet-0.0.4.dist-info/METADATA
simple_google_spreadsheet-0.0.4.dist-info/WHEEL
simple_google_spreadsheet-0.0.4.dist-info/top_level.txt
simple_google_spreadsheet-0.0.4.dist-info/RECORD
