Metadata-Version: 2.1
Name: simple-google-spreadsheet
Version: 0.0.4
Summary: A module class to simplify the integration of your data with a sheet in Google SpreadSheet
Home-page: https://github.com/mbiemann/simple-google-spreadsheet
Author: Marcell Biemann
Author-email: mbiemann@gmail.com
License: UNKNOWN
Project-URL: Bug Tracker, https://github.com/mbiemann/simple-google-spreadsheet/issues
Platform: UNKNOWN
Classifier: Programming Language :: Python :: 3
Classifier: License :: OSI Approved :: MIT License
Classifier: Operating System :: OS Independent
Requires-Python: >=3.6
License-File: LICENSE
Requires-Dist: google-api-python-client
Requires-Dist: google-auth-httplib2
Requires-Dist: google-auth-oauthlib
